ipparser/__init__.py
ipparser/nmap.py
ipparser-1.0.2.dist-info/LICENSE
ipparser-1.0.2.dist-info/METADATA
ipparser-1.0.2.dist-info/WHEEL
ipparser-1.0.2.dist-info/top_level.txt
ipparser-1.0.2.dist-info/RECORD
