Metadata-Version: 2.1
Name: ipparser
Version: 1.0.2
Summary: Lightweight package to parse host inputs for iteration.
Home-page: https://github.com/m8sec/ipparser
Author: m8sec
License: BSD 3-clause
Classifier: Programming Language :: Python :: 3
Classifier: Intended Audience :: Developers
Classifier: License :: OSI Approved :: BSD License
License-File: LICENSE
Requires-Dist: dnspython
